{"data":{"symbol":"QNST","companyName":"QuinStreet, Inc. Common Stock","stockType":"Common Stock","exchange":"NASDAQ-GS","isNasdaqListed":true,"isNasdaq100":false,"isHeld":false,"primaryData":{"lastSalePrice":"$17.16","netChange":"-0.13","percentageChange":"-0.75%","deltaIndicator":"down","lastTradeTimestamp":"Feb 10, 2023","isRealTime":false,"bidPrice":"N/A","askPrice":"N/A","volume":"452,681"},"secondaryData":null,"marketStatus":"Closed","assetClass":"STOCKS","keyStats":null,"notifications":[]},"message":null,"status":{"rCode":200,"bCodeMessage":null,"developerMessage":null}}