{"data":{"dividendHeaderValues":[{"label":"EX-DIVIDEND DATE","value":"N/A"},{"label":"DIVIDEND YIELD","value":"N/A"},{"label":"ANNUAL DIVIDEND","value":"N/A"},{"label":"P/E RATIO","value":"0"}],"exDividendDate":"N/A","dividendPaymentDate":"N/A","yield":"N/A","annualizedDividend":"N/A","payoutRatio":"N/A","dividends":{"headers":{"exOrEffDate":"Ex/EFF DATE","type":"TYPE","amount":"CASH AMOUNT","declarationDate":"DECLARATION DATE","recordDate":"RECORD DATE","paymentDate":"PAYMENT DATE"},"rows":[{"exOrEffDate":"01/29/2014","type":"CASH","amount":"$3.013","declarationDate":"01/29/2014","recordDate":"01/28/2014","paymentDate":"02/05/2014","currency":"USD"},{"exOrEffDate":"07/18/2013","type":"CASH","amount":"$3.006","declarationDate":"10/03/2013","recordDate":"07/22/2013","paymentDate":"07/25/2013","currency":"USD"}]}},"message":null,"status":{"rCode":200,"bCodeMessage":null,"developerMessage":null}}