{"data":{"dividendHeaderValues":[{"label":"EX-DIVIDEND DATE","value":"05/19/2022"},{"label":"DIVIDEND YIELD","value":"2.89%"},{"label":"ANNUAL DIVIDEND","value":"$3.9936"},{"label":"P/E RATIO","value":"8.39"}],"exDividendDate":"05/19/2022","dividendPaymentDate":"06/10/2022","yield":"2.89%","annualizedDividend":"3.9936","payoutRatio":"8.39","dividends":{"headers":{"exOrEffDate":"Ex/EFF DATE","type":"TYPE","amount":"CASH AMOUNT","declarationDate":"DECLARATION DATE","recordDate":"RECORD DATE","paymentDate":"PAYMENT DATE"},"rows":[{"exOrEffDate":"05/19/2022","type":"CASH","amount":"$3.9936","declarationDate":"04/28/2022","recordDate":"05/20/2022","paymentDate":"06/10/2022","currency":"USD"},{"exOrEffDate":"09/14/2021","type":"CASH","amount":"$1.2087","declarationDate":"08/26/2021","recordDate":"09/15/2021","paymentDate":"10/07/2021","currency":"USD"},{"exOrEffDate":"04/09/2020","type":"CASH","amount":"$8.8026","declarationDate":"02/27/2020","recordDate":"04/13/2020","paymentDate":"05/08/2020","currency":"USD"},{"exOrEffDate":"10/22/2019","type":"CASH","amount":"$2.3623","declarationDate":"09/26/2019","recordDate":"10/23/2019","paymentDate":"11/22/2019","currency":"USD"},{"exOrEffDate":"04/15/2019","type":"CASH","amount":"$6.0332","declarationDate":"02/28/2019","recordDate":"04/16/2019","paymentDate":"05/10/2019","currency":"USD"},{"exOrEffDate":"04/17/2018","type":"CASH","amount":"$4.304","declarationDate":"03/01/2018","recordDate":"04/18/2018","paymentDate":"05/11/2018","currency":"USD"},{"exOrEffDate":"11/13/2017","type":"CASH","amount":"$4.8354","declarationDate":"10/25/2017","recordDate":"11/14/2017","paymentDate":"11/24/2017","currency":"USD"},{"exOrEffDate":"11/13/2017","type":"CASH","amount":"$4.8354","declarationDate":"10/25/2017","recordDate":"11/14/2017","paymentDate":"11/24/2017","currency":"USD"},{"exOrEffDate":"04/13/2017","type":"CASH","amount":"$3.7376","declarationDate":"02/22/2017","recordDate":"04/18/2017","paymentDate":"05/12/2017","currency":"USD"},{"exOrEffDate":"04/14/2016","type":"CASH","amount":"$2.316","declarationDate":"02/24/2016","recordDate":"04/18/2016","paymentDate":"05/13/2016","currency":"USD"},{"exOrEffDate":"04/17/2015","type":"CASH","amount":"$2.1873","declarationDate":"02/26/2015","recordDate":"04/21/2015","paymentDate":"05/15/2015","currency":"USD"},{"exOrEffDate":"04/17/2014","type":"CASH","amount":"$1.90","declarationDate":"02/27/2014","recordDate":"04/22/2014","paymentDate":"05/16/2014","currency":"USD"},{"exOrEffDate":"04/12/2013","type":"CASH","amount":"$2.60","declarationDate":"02/28/2013","recordDate":"04/16/2013","paymentDate":"05/10/2013","currency":"USD"},{"exOrEffDate":"04/16/2012","type":"CASH","amount":"$2.30","declarationDate":"02/23/2012","recordDate":"04/18/2012","paymentDate":"05/11/2012","currency":"USD"},{"exOrEffDate":"04/15/2011","type":"CASH","amount":"$1.95","declarationDate":"02/23/2011","recordDate":"04/19/2011","paymentDate":"05/13/2011","currency":"USD"},{"exOrEffDate":"04/14/2010","type":"CASH","amount":"$1.70","declarationDate":"02/24/2010","recordDate":"04/16/2010","paymentDate":"05/11/2010","currency":"USD"},{"exOrEffDate":"04/16/2009","type":"CASH","amount":"$1.50","declarationDate":"02/27/2009","recordDate":"04/20/2009","paymentDate":"05/13/2009","currency":"USD"},{"exOrEffDate":"04/14/2008","type":"CASH","amount":"$1.50","declarationDate":"N/A","recordDate":"04/16/2008","paymentDate":"05/07/2008","currency":"USD"},{"exOrEffDate":"04/17/2007","type":"CASH","amount":"$1.30","declarationDate":"N/A","recordDate":"04/19/2007","paymentDate":"05/07/2007","currency":"USD"},{"exOrEffDate":"04/10/2006","type":"CASH","amount":"$1.10","declarationDate":"N/A","recordDate":"04/12/2006","paymentDate":"05/03/2006","currency":"USD"},{"exOrEffDate":"04/15/2005","type":"CASH","amount":"$0.80","declarationDate":"N/A","recordDate":"04/19/2005","paymentDate":"05/02/2005","currency":"USD"},{"exOrEffDate":"04/14/2004","type":"CASH","amount":"$0.40","declarationDate":"N/A","recordDate":"04/16/2004","paymentDate":"04/30/2004","currency":"USD"},{"exOrEffDate":"04/14/2003","type":"CASH","amount":"$0.30","declarationDate":"N/A","recordDate":"04/16/2003","paymentDate":"04/30/2003","currency":"USD"},{"exOrEffDate":"04/03/2002","type":"CASH","amount":"$0.20","declarationDate":"N/A","recordDate":"04/05/2002","paymentDate":"05/02/2002","currency":"USD"},{"exOrEffDate":"12/12/2001","type":"CASH","amount":"$0.20","declarationDate":"N/A","recordDate":"12/14/2001","paymentDate":"01/15/2002","currency":"USD"},{"exOrEffDate":"04/09/2001","type":"CASH","amount":"$0.10","declarationDate":"N/A","recordDate":"04/11/2001","paymentDate":"05/02/2001","currency":"USD"},{"exOrEffDate":"04/11/2000","type":"CASH","amount":"$0.10","declarationDate":"N/A","recordDate":"04/13/2000","paymentDate":"04/27/2000","currency":"USD"},{"exOrEffDate":"04/06/1999","type":"CASH","amount":"$0.20","declarationDate":"04/01/1999","recordDate":"04/08/1999","paymentDate":"04/30/1999","currency":"USD"},{"exOrEffDate":"03/27/1998","type":"CASH","amount":"$0.45","declarationDate":"02/27/1998","recordDate":"03/31/1998","paymentDate":"04/24/1998","currency":"USD"},{"exOrEffDate":"03/19/1997","type":"CASH","amount":"$0.50","declarationDate":"02/21/1997","recordDate":"03/21/1997","paymentDate":"04/14/1997","currency":"USD"},{"exOrEffDate":"03/27/1996","type":"CASH","amount":"$0.55","declarationDate":"03/14/1996","recordDate":"03/29/1996","paymentDate":"04/12/1996","currency":"USD"}]}},"message":null,"status":{"rCode":200,"bCodeMessage":null,"developerMessage":null}}