{"data":{"dividendHeaderValues":[{"label":"EX-DIVIDEND DATE","value":"N/A"},{"label":"DIVIDEND YIELD","value":"N/A"},{"label":"ANNUAL DIVIDEND","value":"N/A"},{"label":"P/E RATIO","value":"N/A"}],"exDividendDate":"N/A","dividendPaymentDate":"03/31/2017","yield":"N/A","annualizedDividend":"N/A","payoutRatio":"N/A","dividends":{"headers":{"exOrEffDate":"Ex/EFF DATE","type":"TYPE","amount":"CASH AMOUNT","declarationDate":"DECLARATION DATE","recordDate":"RECORD DATE","paymentDate":"PAYMENT DATE"},"rows":[{"exOrEffDate":"03/22/2017","type":"CASH","amount":"$0.1918","declarationDate":"03/13/2017","recordDate":"03/24/2017","paymentDate":"03/31/2017","currency":"USD"}]}},"message":null,"status":{"rCode":200,"bCodeMessage":null,"developerMessage":null}}