{"data":{"symbol":"CGAU","companyName":"Centerra Gold Inc. Common Shares","stockType":"Common Shares","exchange":"NYSE","isNasdaqListed":false,"isNasdaq100":false,"isHeld":false,"primaryData":{"lastSalePrice":"$6.42","netChange":"-0.09","percentageChange":"-1.38%","deltaIndicator":"down","lastTradeTimestamp":"Feb 10, 2023","isRealTime":false,"bidPrice":"N/A","askPrice":"N/A","volume":"143,748"},"secondaryData":null,"marketStatus":"Closed","assetClass":"STOCKS","keyStats":null,"notifications":[{"headline":"UPCOMING EVENTS","eventTypes":[{"message":"Earnings Date : 02/24/2023","eventName":"Earnings Date","url":{"label":"Earnings Date : 02/24/2023","value":"/market-activity/stocks/CGAU/earnings"},"id":"upcoming_events"}]}]},"message":null,"status":{"rCode":200,"bCodeMessage":null,"developerMessage":null}}