{"data":{"ModuleTitle":{"label":"Module Title","value":"Company Description"},"CompanyName":{"label":"Company Name","value":"Apple Inc."},"Symbol":{"label":"Symbol","value":"AAPL"},"Address":{"label":"Address","value":"ONE APPLE PARK WAY, CUPERTINO, California, 95014, United States"},"Phone":{"label":"Phone","value":"+1 408 996-1010"},"Industry":{"label":"Industry","value":"Computer Manufacturing"},"Sector":{"label":"Sector","value":"Technology"},"Region":{"label":"Region","value":"North America"},"CompanyDescription":{"label":"Company Description","value":"Apple designs a wide variety of consumer electronic devices, including smartphones (iPhone), tablets (iPad), PCs (Mac), smartwatches (Apple Watch), and AirPods. The iPhone makes up most of Apple's total revenue. In addition, Apple offers its customers a variety of services such as Apple Music, iCloud, Apple Care, Apple TV+, Apple Arcade, Apple Fitness, Apple Card, and Apple Pay, among others. Apple's products include internally developed software and semiconductors, and the firm is well known for its integration of hardware, software, semiconductors, and services. Apple's products are distributed online as well as through company-owned stores and third-party retailers. The company generates roughly 40% of its revenue from the Americas, with the remainder earned internationally."},"CompanyUrl":{"label":"Company Url","value":"https://www.apple.com"},"KeyExecutives":{"label":"Key Executives","value":[{"name":"Jeffrey E. Williams","title":"Chief Operating Officer"},{"name":"Kevin M. Lynch","title":"Vice President-Technology"},{"name":"Timothy Donald Cook","title":"Chief Executive Officer &amp; Director"}]}},"message":null,"status":{"rCode":200,"bCodeMessage":null,"developerMessage":null}}