{"data":{"symbol":"AIRTP","companyName":"Air T, Inc. Air T Funding Alpha Income Trust Preferred Securities","stockType":"Trust Preferred Securities Trust Preferred","exchange":"NASDAQ-GM","isNasdaqListed":true,"isNasdaq100":false,"isHeld":false,"primaryData":{"lastSalePrice":"$23.295","netChange":"UNCH","percentageChange":"","deltaIndicator":"unch","lastTradeTimestamp":"Feb 10, 2023","isRealTime":false,"bidPrice":"N/A","askPrice":"N/A","volume":"N/A"},"secondaryData":null,"marketStatus":"Closed","assetClass":"STOCKS","keyStats":null,"notifications":[]},"message":null,"status":{"rCode":200,"bCodeMessage":null,"developerMessage":null}}