{"data":{"ModuleTitle":{"label":"Module Title","value":"Company Description"},"CompanyName":{"label":"Company Name","value":"Alarm.com Holdings, Inc."},"Symbol":{"label":"Symbol","value":"ALRM"},"Address":{"label":"Address","value":"8281 GREENSBORO DRIVE SUITE 100, TYSONS, Virginia, 22102, United States"},"Phone":{"label":"Phone","value":"+1 877 389-4033"},"Industry":{"label":"Industry","value":"Computer Software: Prepackaged Software"},"Sector":{"label":"Sector","value":"Technology"},"Region":{"label":"Region","value":"North America"},"CompanyDescription":{"label":"Company Description","value":"Alarm.com Holdings Inc provides a software-as-a-service, or SaaS, platform solution for the connected home. The platform allows home and business owners to secure their properties and automate and control an array of connected devices. SaaS and license fees from service providers, who resell these services and pay Alarm.com a monthly subscription, are the largest sources of revenue for the firm. The SaaS platform also caters to the service provider by offering enterprise-grade business-management solutions to expand and manage its customer base. A large majority of the firm's revenue is generated in the United States and Canada."},"CompanyUrl":{"label":"Company Url","value":"https://www.alarm.com"},"KeyExecutives":{"label":"Key Executives","value":[{"name":"Jean-Paul Martin","title":"Chief Technology Officer"},{"name":"Stephen S. Trundle","title":"Chief Executive Officer &amp; Director"}]}},"message":null,"status":{"rCode":200,"bCodeMessage":null,"developerMessage":null}}