{"data":{"ModuleTitle":{"label":"Module Title","value":"Company Description"},"CompanyName":{"label":"Company Name","value":"ARKO Corp."},"Symbol":{"label":"Symbol","value":"ARKOW"},"Address":{"label":"Address","value":"8565 MAGELLAN PARKWAY SUITE 400, RICHMOND, Virginia, 23227-1150, United States"},"Phone":{"label":"Phone","value":"+1 804 730-1568"},"Industry":{"label":"Industry","value":"Oil Refining/Marketing"},"Sector":{"label":"Sector","value":"Energy"},"Region":{"label":"Region","value":"North America"},"CompanyDescription":{"label":"Company Description","value":"ARKO Corp operates as a holding company. The company, through its subsidiaries, owns and operates convenience stores in the United States. Some of its regional store brands include Stop, Admiral, Apple Market, BreadBox, E-Z Mart, fas mart, Li'l Cricket, and Next Door Store. Its retail store offers hot food service, beverages, cigarettes &amp; other tobacco products, candy, salty snacks, grocery, beer, and general merchandise. ARKO operates in three segments: Retail, Wholesale, and GPM Petroleum. The company derives the majority of its revenue from retail and wholesale distribution of fuel."},"CompanyUrl":{"label":"Company Url","value":"https://www.arkocorp.com"},"KeyExecutives":{"label":"Key Executives","value":[]}},"message":null,"status":{"rCode":200,"bCodeMessage":null,"developerMessage":null}}