{"data":{"symbol":"NVVE","companyName":"Nuvve Holding Corp. Common Stock","stockType":"Common Stock","exchange":"NASDAQ-CM","isNasdaqListed":true,"isNasdaq100":false,"isHeld":false,"primaryData":{"lastSalePrice":"$1.14","netChange":"-0.05","percentageChange":"-4.2%","deltaIndicator":"down","lastTradeTimestamp":"Feb 10, 2023","isRealTime":false,"bidPrice":"N/A","askPrice":"N/A","volume":"190,917"},"secondaryData":null,"marketStatus":"Closed","assetClass":"STOCKS","keyStats":null,"notifications":[]},"message":null,"status":{"rCode":200,"bCodeMessage":null,"developerMessage":null}}