{"data":{"symbol":"SACH","companyName":"Sachem Capital Corp. Common Shares","stockType":"Common Shares","exchange":"AMEX","isNasdaqListed":false,"isNasdaq100":false,"isHeld":false,"primaryData":{"lastSalePrice":"$3.72","netChange":"-0.06","percentageChange":"-1.59%","deltaIndicator":"down","lastTradeTimestamp":"Feb 10, 2023","isRealTime":false,"bidPrice":"N/A","askPrice":"N/A","volume":"355,610"},"secondaryData":null,"marketStatus":"Closed","assetClass":"STOCKS","keyStats":null,"notifications":[]},"message":null,"status":{"rCode":200,"bCodeMessage":null,"developerMessage":null}}