{"data":{"symbol":"WLKP","companyName":"Westlake Chemical Partners LP Common Units representing limited partner interests","stockType":"Common Units representing limited partner interests Equity Units","exchange":"NYSE","isNasdaqListed":false,"isNasdaq100":false,"isHeld":false,"primaryData":{"lastSalePrice":"$24.21","netChange":"+0.21","percentageChange":"+0.88%","deltaIndicator":"up","lastTradeTimestamp":"Feb 10, 2023","isRealTime":false,"bidPrice":"N/A","askPrice":"N/A","volume":"14,647"},"secondaryData":null,"marketStatus":"Closed","assetClass":"STOCKS","keyStats":null,"notifications":[{"headline":"UPCOMING EVENTS","eventTypes":[{"message":"Earnings Date : 02/21/2023","eventName":"Earnings Date","url":{"label":"Earnings Date : 02/21/2023","value":"/market-activity/stocks/WLKP/earnings"},"id":"upcoming_events"}]}]},"message":null,"status":{"rCode":200,"bCodeMessage":null,"developerMessage":null}}