{"data":{"dividendHeaderValues":[{"label":"EX-DIVIDEND DATE","value":"02/01/2023"},{"label":"DIVIDEND YIELD","value":"4.66%"},{"label":"ANNUAL DIVIDEND","value":"$0.48"},{"label":"P/E RATIO","value":"28.47"}],"exDividendDate":"02/01/2023","dividendPaymentDate":"02/14/2023","yield":"4.66%","annualizedDividend":"0.48","payoutRatio":"28.47","dividends":{"headers":{"exOrEffDate":"Ex/EFF DATE","type":"TYPE","amount":"CASH AMOUNT","declarationDate":"DECLARATION DATE","recordDate":"RECORD DATE","paymentDate":"PAYMENT DATE"},"rows":[{"exOrEffDate":"03/01/2023","type":"CASH","amount":"$0.04","declarationDate":"12/15/2022","recordDate":"03/02/2023","paymentDate":"03/14/2023","currency":"USD"},{"exOrEffDate":"02/01/2023","type":"CASH","amount":"$0.04","declarationDate":"12/15/2022","recordDate":"02/02/2023","paymentDate":"02/14/2023","currency":"USD"},{"exOrEffDate":"01/03/2023","type":"CASH","amount":"$0.04","declarationDate":"12/15/2022","recordDate":"01/04/2023","paymentDate":"01/11/2023","currency":"USD"},{"exOrEffDate":"12/01/2022","type":"CASH","amount":"$0.04","declarationDate":"07/27/2022","recordDate":"12/02/2022","paymentDate":"12/14/2022","currency":"USD"},{"exOrEffDate":"11/01/2022","type":"CASH","amount":"$0.04","declarationDate":"07/27/2022","recordDate":"11/02/2022","paymentDate":"11/14/2022","currency":"USD"},{"exOrEffDate":"10/03/2022","type":"CASH","amount":"$0.04","declarationDate":"07/27/2022","recordDate":"10/04/2022","paymentDate":"10/12/2022","currency":"USD"},{"exOrEffDate":"09/02/2022","type":"CASH","amount":"$0.04","declarationDate":"05/23/2022","recordDate":"09/06/2022","paymentDate":"09/14/2022","currency":"USD"},{"exOrEffDate":"08/01/2022","type":"CASH","amount":"$0.04","declarationDate":"05/23/2022","recordDate":"08/02/2022","paymentDate":"08/12/2022","currency":"USD"},{"exOrEffDate":"07/01/2022","type":"CASH","amount":"$0.04","declarationDate":"05/23/2022","recordDate":"07/05/2022","paymentDate":"07/13/2022","currency":"USD"},{"exOrEffDate":"06/01/2022","type":"CASH","amount":"$0.04","declarationDate":"02/22/2022","recordDate":"06/02/2022","paymentDate":"06/14/2022","currency":"USD"},{"exOrEffDate":"05/02/2022","type":"CASH","amount":"$0.04","declarationDate":"02/22/2022","recordDate":"05/03/2022","paymentDate":"05/12/2022","currency":"USD"},{"exOrEffDate":"04/01/2022","type":"CASH","amount":"$0.04","declarationDate":"02/22/2022","recordDate":"04/04/2022","paymentDate":"04/14/2022","currency":"USD"},{"exOrEffDate":"03/01/2022","type":"CASH","amount":"$0.035833","declarationDate":"12/16/2021","recordDate":"03/02/2022","paymentDate":"03/11/2022","currency":"USD"},{"exOrEffDate":"02/01/2022","type":"CASH","amount":"$0.035833","declarationDate":"12/16/2021","recordDate":"02/02/2022","paymentDate":"02/11/2022","currency":"USD"},{"exOrEffDate":"01/03/2022","type":"CASH","amount":"$0.035833","declarationDate":"12/16/2021","recordDate":"01/04/2022","paymentDate":"01/13/2022","currency":"USD"},{"exOrEffDate":"12/01/2021","type":"CASH","amount":"$0.035833","declarationDate":"09/13/2021","recordDate":"12/02/2021","paymentDate":"12/13/2021","currency":"USD"},{"exOrEffDate":"11/01/2021","type":"CASH","amount":"$0.035833","declarationDate":"09/13/2021","recordDate":"11/02/2021","paymentDate":"11/12/2021","currency":"USD"},{"exOrEffDate":"10/01/2021","type":"CASH","amount":"$0.035833","declarationDate":"09/13/2021","recordDate":"10/04/2021","paymentDate":"10/14/2021","currency":"USD"},{"exOrEffDate":"09/01/2021","type":"CASH","amount":"$0.035833","declarationDate":"06/11/2021","recordDate":"09/02/2021","paymentDate":"09/14/2021","currency":"USD"},{"exOrEffDate":"08/02/2021","type":"CASH","amount":"$0.035833","declarationDate":"06/11/2021","recordDate":"08/03/2021","paymentDate":"08/12/2021","currency":"USD"},{"exOrEffDate":"07/01/2021","type":"CASH","amount":"$0.035833","declarationDate":"06/11/2021","recordDate":"07/02/2021","paymentDate":"07/14/2021","currency":"USD"},{"exOrEffDate":"06/01/2021","type":"CASH","amount":"$0.035833","declarationDate":"03/26/2021","recordDate":"06/02/2021","paymentDate":"06/10/2021","currency":"USD"},{"exOrEffDate":"05/03/2021","type":"CASH","amount":"$0.035833","declarationDate":"03/26/2021","recordDate":"05/04/2021","paymentDate":"05/13/2021","currency":"USD"},{"exOrEffDate":"04/01/2021","type":"CASH","amount":"$0.035833","declarationDate":"03/26/2021","recordDate":"04/05/2021","paymentDate":"04/14/2021","currency":"USD"},{"exOrEffDate":"03/01/2021","type":"CASH","amount":"$0.035","declarationDate":"12/10/2020","recordDate":"03/02/2021","paymentDate":"03/11/2021","currency":"USD"},{"exOrEffDate":"02/01/2021","type":"CASH","amount":"$0.035","declarationDate":"12/10/2020","recordDate":"02/02/2021","paymentDate":"02/11/2021","currency":"USD"},{"exOrEffDate":"01/04/2021","type":"CASH","amount":"$0.035","declarationDate":"12/10/2020","recordDate":"01/05/2021","paymentDate":"01/14/2021","currency":"USD"},{"exOrEffDate":"12/01/2020","type":"CASH","amount":"$0.035","declarationDate":"09/22/2020","recordDate":"12/02/2020","paymentDate":"12/10/2020","currency":"USD"},{"exOrEffDate":"11/02/2020","type":"CASH","amount":"$0.035","declarationDate":"09/22/2020","recordDate":"11/03/2020","paymentDate":"11/12/2020","currency":"USD"},{"exOrEffDate":"10/05/2020","type":"CASH","amount":"$0.035","declarationDate":"09/22/2020","recordDate":"10/06/2020","paymentDate":"10/15/2020","currency":"USD"},{"exOrEffDate":"08/31/2020","type":"CASH","amount":"$0.035","declarationDate":"06/16/2020","recordDate":"09/01/2020","paymentDate":"09/10/2020","currency":"USD"},{"exOrEffDate":"08/03/2020","type":"CASH","amount":"$0.035","declarationDate":"06/16/2020","recordDate":"08/04/2020","paymentDate":"08/13/2020","currency":"USD"},{"exOrEffDate":"07/01/2020","type":"CASH","amount":"$0.035","declarationDate":"06/16/2020","recordDate":"07/02/2020","paymentDate":"07/10/2020","currency":"USD"},{"exOrEffDate":"06/01/2020","type":"CASH","amount":"$0.035","declarationDate":"03/24/2020","recordDate":"06/02/2020","paymentDate":"06/12/2020","currency":"USD"},{"exOrEffDate":"05/01/2020","type":"CASH","amount":"$0.035","declarationDate":"03/24/2020","recordDate":"05/04/2020","paymentDate":"05/13/2020","currency":"USD"},{"exOrEffDate":"04/06/2020","type":"CASH","amount":"$0.035","declarationDate":"03/24/2020","recordDate":"04/07/2020","paymentDate":"04/15/2020","currency":"USD"},{"exOrEffDate":"03/02/2020","type":"CASH","amount":"$0.095","declarationDate":"12/18/2019","recordDate":"03/03/2020","paymentDate":"03/13/2020","currency":"USD"},{"exOrEffDate":"02/03/2020","type":"CASH","amount":"$0.095","declarationDate":"12/18/2019","recordDate":"02/04/2020","paymentDate":"02/13/2020","currency":"USD"},{"exOrEffDate":"01/02/2020","type":"CASH","amount":"$0.095","declarationDate":"12/18/2019","recordDate":"01/03/2020","paymentDate":"01/15/2020","currency":"USD"},{"exOrEffDate":"12/02/2019","type":"CASH","amount":"$0.095","declarationDate":"09/23/2019","recordDate":"12/03/2019","paymentDate":"12/12/2019","currency":"USD"},{"exOrEffDate":"11/01/2019","type":"CASH","amount":"$0.095","declarationDate":"09/23/2019","recordDate":"11/04/2019","paymentDate":"11/14/2019","currency":"USD"},{"exOrEffDate":"10/01/2019","type":"CASH","amount":"$0.095","declarationDate":"09/23/2019","recordDate":"10/02/2019","paymentDate":"10/10/2019","currency":"USD"},{"exOrEffDate":"08/30/2019","type":"CASH","amount":"$0.095","declarationDate":"05/15/2019","recordDate":"09/03/2019","paymentDate":"09/13/2019","currency":"USD"},{"exOrEffDate":"08/01/2019","type":"CASH","amount":"$0.095","declarationDate":"05/15/2019","recordDate":"08/02/2019","paymentDate":"08/13/2019","currency":"USD"},{"exOrEffDate":"07/01/2019","type":"CASH","amount":"$0.095","declarationDate":"05/15/2019","recordDate":"07/02/2019","paymentDate":"07/12/2019","currency":"USD"},{"exOrEffDate":"06/03/2019","type":"CASH","amount":"$0.095","declarationDate":"03/25/2019","recordDate":"06/04/2019","paymentDate":"06/13/2019","currency":"USD"},{"exOrEffDate":"05/01/2019","type":"CASH","amount":"$0.095","declarationDate":"03/25/2019","recordDate":"05/02/2019","paymentDate":"05/10/2019","currency":"USD"},{"exOrEffDate":"04/03/2019","type":"CASH","amount":"$0.095","declarationDate":"03/25/2019","recordDate":"04/04/2019","paymentDate":"04/10/2019","currency":"USD"},{"exOrEffDate":"03/01/2019","type":"CASH","amount":"$0.095","declarationDate":"12/20/2018","recordDate":"03/04/2019","paymentDate":"03/14/2019","currency":"USD"},{"exOrEffDate":"02/01/2019","type":"CASH","amount":"$0.095","declarationDate":"12/20/2018","recordDate":"02/04/2019","paymentDate":"02/14/2019","currency":"USD"},{"exOrEffDate":"12/31/2018","type":"CASH","amount":"$0.095","declarationDate":"12/20/2018","recordDate":"01/02/2019","paymentDate":"01/11/2019","currency":"USD"},{"exOrEffDate":"12/03/2018","type":"CASH","amount":"$0.095","declarationDate":"09/19/2018","recordDate":"12/04/2018","paymentDate":"12/13/2018","currency":"USD"},{"exOrEffDate":"11/01/2018","type":"CASH","amount":"$0.095","declarationDate":"09/19/2018","recordDate":"11/02/2018","paymentDate":"11/13/2018","currency":"USD"},{"exOrEffDate":"10/01/2018","type":"CASH","amount":"$0.095","declarationDate":"09/19/2018","recordDate":"10/02/2018","paymentDate":"10/12/2018","currency":"USD"},{"exOrEffDate":"08/31/2018","type":"CASH","amount":"$0.095","declarationDate":"06/13/2018","recordDate":"09/04/2018","paymentDate":"09/14/2018","currency":"USD"},{"exOrEffDate":"08/01/2018","type":"CASH","amount":"$0.095","declarationDate":"06/13/2018","recordDate":"08/02/2018","paymentDate":"08/14/2018","currency":"USD"},{"exOrEffDate":"07/02/2018","type":"CASH","amount":"$0.095","declarationDate":"06/13/2018","recordDate":"07/03/2018","paymentDate":"07/12/2018","currency":"USD"},{"exOrEffDate":"06/01/2018","type":"CASH","amount":"$0.095","declarationDate":"03/06/2018","recordDate":"06/04/2018","paymentDate":"06/13/2018","currency":"USD"},{"exOrEffDate":"05/01/2018","type":"CASH","amount":"$0.095","declarationDate":"03/06/2018","recordDate":"05/02/2018","paymentDate":"05/11/2018","currency":"USD"},{"exOrEffDate":"04/02/2018","type":"CASH","amount":"$0.095","declarationDate":"03/06/2018","recordDate":"04/03/2018","paymentDate":"04/12/2018","currency":"USD"},{"exOrEffDate":"03/01/2018","type":"CASH","amount":"$0.095","declarationDate":"12/14/2017","recordDate":"03/02/2018","paymentDate":"03/13/2018","currency":"USD"},{"exOrEffDate":"02/02/2018","type":"CASH","amount":"$0.095","declarationDate":"12/14/2017","recordDate":"02/05/2018","paymentDate":"02/14/2018","currency":"USD"},{"exOrEffDate":"12/29/2017","type":"CASH","amount":"$0.095","declarationDate":"12/14/2017","recordDate":"01/02/2018","paymentDate":"01/11/2018","currency":"USD"},{"exOrEffDate":"12/04/2017","type":"CASH","amount":"$0.095","declarationDate":"09/13/2017","recordDate":"12/05/2017","paymentDate":"12/14/2017","currency":"USD"},{"exOrEffDate":"11/02/2017","type":"CASH","amount":"$0.095","declarationDate":"09/13/2017","recordDate":"11/03/2017","paymentDate":"11/13/2017","currency":"USD"},{"exOrEffDate":"10/03/2017","type":"CASH","amount":"$0.095","declarationDate":"09/13/2017","recordDate":"10/04/2017","paymentDate":"10/12/2017","currency":"USD"},{"exOrEffDate":"08/31/2017","type":"CASH","amount":"$0.095","declarationDate":"06/15/2017","recordDate":"09/05/2017","paymentDate":"09/13/2017","currency":"USD"},{"exOrEffDate":"08/01/2017","type":"CASH","amount":"$0.095","declarationDate":"06/15/2017","recordDate":"08/03/2017","paymentDate":"08/11/2017","currency":"USD"},{"exOrEffDate":"06/30/2017","type":"CASH","amount":"$0.095","declarationDate":"06/15/2017","recordDate":"07/05/2017","paymentDate":"07/12/2017","currency":"USD"},{"exOrEffDate":"06/01/2017","type":"CASH","amount":"$0.095","declarationDate":"03/20/2017","recordDate":"06/05/2017","paymentDate":"06/13/2017","currency":"USD"},{"exOrEffDate":"05/01/2017","type":"CASH","amount":"$0.095","declarationDate":"03/20/2017","recordDate":"05/03/2017","paymentDate":"05/11/2017","currency":"USD"},{"exOrEffDate":"04/03/2017","type":"CASH","amount":"$0.095","declarationDate":"03/20/2017","recordDate":"04/05/2017","paymentDate":"04/13/2017","currency":"USD"},{"exOrEffDate":"03/01/2017","type":"CASH","amount":"$0.095","declarationDate":"12/21/2016","recordDate":"03/03/2017","paymentDate":"03/10/2017","currency":"USD"},{"exOrEffDate":"02/01/2017","type":"CASH","amount":"$0.095","declarationDate":"12/21/2016","recordDate":"02/03/2017","paymentDate":"02/10/2017","currency":"USD"},{"exOrEffDate":"12/30/2016","type":"CASH","amount":"$0.095","declarationDate":"12/21/2016","recordDate":"01/04/2017","paymentDate":"01/12/2017","currency":"USD"},{"exOrEffDate":"11/29/2016","type":"CASH","amount":"$0.095","declarationDate":"09/22/2016","recordDate":"12/01/2016","paymentDate":"12/09/2016","currency":"USD"},{"exOrEffDate":"10/28/2016","type":"CASH","amount":"$0.095","declarationDate":"09/22/2016","recordDate":"11/01/2016","paymentDate":"11/11/2016","currency":"USD"},{"exOrEffDate":"09/29/2016","type":"CASH","amount":"$0.095","declarationDate":"09/22/2016","recordDate":"10/03/2016","paymentDate":"10/12/2016","currency":"USD"},{"exOrEffDate":"08/30/2016","type":"CASH","amount":"$0.095","declarationDate":"06/06/2016","recordDate":"09/01/2016","paymentDate":"09/09/2016","currency":"USD"},{"exOrEffDate":"07/28/2016","type":"CASH","amount":"$0.095","declarationDate":"06/06/2016","recordDate":"08/01/2016","paymentDate":"08/09/2016","currency":"USD"},{"exOrEffDate":"06/29/2016","type":"CASH","amount":"$0.095","declarationDate":"06/06/2016","recordDate":"07/01/2016","paymentDate":"07/08/2016","currency":"USD"},{"exOrEffDate":"05/31/2016","type":"CASH","amount":"$0.095","declarationDate":"03/14/2016","recordDate":"06/02/2016","paymentDate":"06/09/2016","currency":"USD"},{"exOrEffDate":"04/28/2016","type":"CASH","amount":"$0.095","declarationDate":"03/14/2016","recordDate":"05/02/2016","paymentDate":"05/09/2016","currency":"USD"},{"exOrEffDate":"03/30/2016","type":"CASH","amount":"$0.095","declarationDate":"03/14/2016","recordDate":"04/01/2016","paymentDate":"04/08/2016","currency":"USD"},{"exOrEffDate":"03/01/2016","type":"CASH","amount":"$0.095","declarationDate":"12/18/2015","recordDate":"03/03/2016","paymentDate":"03/10/2016","currency":"USD"},{"exOrEffDate":"02/01/2016","type":"CASH","amount":"$0.095","declarationDate":"12/18/2015","recordDate":"02/03/2016","paymentDate":"02/10/2016","currency":"USD"},{"exOrEffDate":"01/04/2016","type":"CASH","amount":"$0.095","declarationDate":"12/18/2015","recordDate":"01/06/2016","paymentDate":"01/13/2016","currency":"USD"},{"exOrEffDate":"11/30/2015","type":"CASH","amount":"$0.095","declarationDate":"09/24/2015","recordDate":"12/02/2015","paymentDate":"12/09/2015","currency":"USD"},{"exOrEffDate":"10/29/2015","type":"CASH","amount":"$0.095","declarationDate":"09/24/2015","recordDate":"11/02/2015","paymentDate":"11/09/2015","currency":"USD"},{"exOrEffDate":"10/01/2015","type":"CASH","amount":"$0.095","declarationDate":"09/24/2015","recordDate":"10/05/2015","paymentDate":"10/12/2015","currency":"USD"},{"exOrEffDate":"08/31/2015","type":"CASH","amount":"$0.095","declarationDate":"06/08/2015","recordDate":"09/02/2015","paymentDate":"09/09/2015","currency":"USD"},{"exOrEffDate":"07/30/2015","type":"CASH","amount":"$0.095","declarationDate":"06/08/2015","recordDate":"08/03/2015","paymentDate":"08/10/2015","currency":"USD"},{"exOrEffDate":"06/30/2015","type":"CASH","amount":"$0.095","declarationDate":"06/08/2015","recordDate":"07/02/2015","paymentDate":"07/09/2015","currency":"USD"},{"exOrEffDate":"05/29/2015","type":"CASH","amount":"$0.095","declarationDate":"02/26/2015","recordDate":"06/02/2015","paymentDate":"06/09/2015","currency":"USD"},{"exOrEffDate":"05/01/2015","type":"CASH","amount":"$0.095","declarationDate":"02/26/2015","recordDate":"05/05/2015","paymentDate":"05/12/2015","currency":"USD"},{"exOrEffDate":"03/31/2015","type":"CASH","amount":"$0.095","declarationDate":"02/26/2015","recordDate":"04/02/2015","paymentDate":"04/09/2015","currency":"USD"},{"exOrEffDate":"02/27/2015","type":"CASH","amount":"$0.095","declarationDate":"12/18/2014","recordDate":"03/03/2015","paymentDate":"03/10/2015","currency":"USD"},{"exOrEffDate":"01/30/2015","type":"CASH","amount":"$0.095","declarationDate":"12/16/2014","recordDate":"02/03/2015","paymentDate":"02/10/2015","currency":"USD"},{"exOrEffDate":"01/02/2015","type":"CASH","amount":"$0.095","declarationDate":"12/16/2014","recordDate":"01/06/2015","paymentDate":"01/13/2015","currency":"USD"},{"exOrEffDate":"11/26/2014","type":"CASH","amount":"$0.095","declarationDate":"08/25/2014","recordDate":"12/01/2014","paymentDate":"12/09/2014","currency":"USD"},{"exOrEffDate":"10/30/2014","type":"CASH","amount":"$0.095","declarationDate":"08/25/2014","recordDate":"11/03/2014","paymentDate":"11/11/2014","currency":"USD"},{"exOrEffDate":"09/29/2014","type":"CASH","amount":"$0.095","declarationDate":"08/25/2014","recordDate":"10/01/2014","paymentDate":"10/09/2014","currency":"USD"},{"exOrEffDate":"08/28/2014","type":"CASH","amount":"$0.095","declarationDate":"06/11/2014","recordDate":"09/02/2014","paymentDate":"09/09/2014","currency":"USD"},{"exOrEffDate":"07/30/2014","type":"CASH","amount":"$0.095","declarationDate":"06/11/2014","recordDate":"08/01/2014","paymentDate":"08/08/2014","currency":"USD"},{"exOrEffDate":"06/27/2014","type":"CASH","amount":"$0.095","declarationDate":"06/11/2014","recordDate":"07/01/2014","paymentDate":"07/09/2014","currency":"USD"},{"exOrEffDate":"05/29/2014","type":"CASH","amount":"$0.095","declarationDate":"02/24/2014","recordDate":"06/02/2014","paymentDate":"06/09/2014","currency":"USD"},{"exOrEffDate":"05/01/2014","type":"CASH","amount":"$0.095","declarationDate":"02/24/2014","recordDate":"05/05/2014","paymentDate":"05/12/2014","currency":"USD"},{"exOrEffDate":"03/31/2014","type":"CASH","amount":"$0.095","declarationDate":"02/24/2014","recordDate":"04/02/2014","paymentDate":"04/09/2014","currency":"USD"},{"exOrEffDate":"02/27/2014","type":"CASH","amount":"$0.095","declarationDate":"12/23/2013","recordDate":"03/03/2014","paymentDate":"03/10/2014","currency":"USD"},{"exOrEffDate":"01/30/2014","type":"CASH","amount":"$0.095","declarationDate":"12/23/2013","recordDate":"02/03/2014","paymentDate":"02/10/2014","currency":"USD"},{"exOrEffDate":"01/02/2014","type":"CASH","amount":"$0.095","declarationDate":"12/23/2013","recordDate":"01/06/2014","paymentDate":"01/13/2014","currency":"USD"},{"exOrEffDate":"11/27/2013","type":"CASH","amount":"$0.095","declarationDate":"09/12/2013","recordDate":"12/02/2013","paymentDate":"12/11/2013","currency":"USD"},{"exOrEffDate":"10/30/2013","type":"CASH","amount":"$0.095","declarationDate":"09/12/2013","recordDate":"11/01/2013","paymentDate":"11/08/2013","currency":"USD"},{"exOrEffDate":"09/27/2013","type":"CASH","amount":"$0.095","declarationDate":"09/12/2013","recordDate":"10/01/2013","paymentDate":"10/09/2013","currency":"USD"},{"exOrEffDate":"08/29/2013","type":"CASH","amount":"$0.095","declarationDate":"06/04/2013","recordDate":"09/03/2013","paymentDate":"09/11/2013","currency":"USD"},{"exOrEffDate":"07/30/2013","type":"CASH","amount":"$0.095","declarationDate":"06/04/2013","recordDate":"08/01/2013","paymentDate":"08/09/2013","currency":"USD"},{"exOrEffDate":"06/27/2013","type":"CASH","amount":"$0.095","declarationDate":"06/04/2013","recordDate":"07/01/2013","paymentDate":"07/09/2013","currency":"USD"},{"exOrEffDate":"05/29/2013","type":"CASH","amount":"$0.095","declarationDate":"03/11/2013","recordDate":"05/31/2013","paymentDate":"06/10/2013","currency":"USD"},{"exOrEffDate":"04/26/2013","type":"CASH","amount":"$0.095","declarationDate":"03/11/2013","recordDate":"04/30/2013","paymentDate":"05/09/2013","currency":"USD"},{"exOrEffDate":"03/27/2013","type":"CASH","amount":"$0.095","declarationDate":"03/11/2013","recordDate":"04/01/2013","paymentDate":"04/09/2013","currency":"USD"},{"exOrEffDate":"03/26/2013","type":"CASH","amount":"$0.095","declarationDate":"03/11/2013","recordDate":"03/31/2013","paymentDate":"04/09/2013","currency":"USD"},{"exOrEffDate":"02/26/2013","type":"CASH","amount":"$0.095","declarationDate":"12/19/2012","recordDate":"02/28/2013","paymentDate":"03/08/2013","currency":"USD"},{"exOrEffDate":"01/29/2013","type":"CASH","amount":"$0.095","declarationDate":"12/19/2012","recordDate":"01/31/2013","paymentDate":"02/08/2013","currency":"USD"},{"exOrEffDate":"12/27/2012","type":"CASH","amount":"$0.095","declarationDate":"12/19/2012","recordDate":"12/31/2012","paymentDate":"01/08/2013","currency":"USD"},{"exOrEffDate":"11/28/2012","type":"CASH","amount":"$0.095","declarationDate":"08/07/2012","recordDate":"11/30/2012","paymentDate":"12/07/2012","currency":"USD"},{"exOrEffDate":"10/31/2012","type":"CASH","amount":"$0.095","declarationDate":"08/07/2012","recordDate":"11/01/2012","paymentDate":"11/08/2012","currency":"USD"},{"exOrEffDate":"10/30/2012","type":"CASH","amount":"$0.095","declarationDate":"08/07/2012","recordDate":"11/01/2012","paymentDate":"11/08/2012","currency":"USD"},{"exOrEffDate":"09/27/2012","type":"CASH","amount":"$0.095","declarationDate":"08/07/2012","recordDate":"10/01/2012","paymentDate":"10/08/2012","currency":"USD"},{"exOrEffDate":"08/29/2012","type":"CASH","amount":"$0.095","declarationDate":"05/29/2012","recordDate":"08/31/2012","paymentDate":"09/07/2012","currency":"USD"},{"exOrEffDate":"07/27/2012","type":"CASH","amount":"$0.095","declarationDate":"05/29/2012","recordDate":"07/31/2012","paymentDate":"08/07/2012","currency":"USD"},{"exOrEffDate":"06/27/2012","type":"CASH","amount":"$0.095","declarationDate":"05/29/2012","recordDate":"06/29/2012","paymentDate":"07/06/2012","currency":"USD"},{"exOrEffDate":"05/30/2012","type":"CASH","amount":"$0.095","declarationDate":"02/24/2012","recordDate":"06/01/2012","paymentDate":"06/08/2012","currency":"USD"},{"exOrEffDate":"04/27/2012","type":"CASH","amount":"$0.095","declarationDate":"02/24/2012","recordDate":"05/01/2012","paymentDate":"05/09/2012","currency":"USD"},{"exOrEffDate":"03/29/2012","type":"CASH","amount":"$0.095","declarationDate":"02/24/2012","recordDate":"04/02/2012","paymentDate":"04/09/2012","currency":"USD"},{"exOrEffDate":"02/28/2012","type":"CASH","amount":"$0.095","declarationDate":"12/22/2011","recordDate":"03/01/2012","paymentDate":"03/08/2012","currency":"USD"},{"exOrEffDate":"01/30/2012","type":"CASH","amount":"$0.095","declarationDate":"12/22/2011","recordDate":"02/01/2012","paymentDate":"02/08/2012","currency":"USD"},{"exOrEffDate":"12/28/2011","type":"CASH","amount":"$0.095","declarationDate":"12/22/2011","recordDate":"01/02/2012","paymentDate":"01/09/2012","currency":"USD"},{"exOrEffDate":"11/29/2011","type":"CASH","amount":"$0.095","declarationDate":"08/08/2011","recordDate":"12/01/2011","paymentDate":"12/08/2011","currency":"USD"},{"exOrEffDate":"10/28/2011","type":"CASH","amount":"$0.095","declarationDate":"08/08/2011","recordDate":"11/01/2011","paymentDate":"11/08/2011","currency":"USD"},{"exOrEffDate":"09/28/2011","type":"CASH","amount":"$0.095","declarationDate":"08/08/2011","recordDate":"10/01/2011","paymentDate":"10/07/2011","currency":"USD"},{"exOrEffDate":"08/30/2011","type":"CASH","amount":"$0.095","declarationDate":"05/16/2011","recordDate":"09/01/2011","paymentDate":"09/08/2011","currency":"USD"},{"exOrEffDate":"07/28/2011","type":"CASH","amount":"$0.095","declarationDate":"05/16/2011","recordDate":"08/01/2011","paymentDate":"08/08/2011","currency":"USD"},{"exOrEffDate":"06/29/2011","type":"CASH","amount":"$0.095","declarationDate":"05/16/2011","recordDate":"07/01/2011","paymentDate":"07/08/2011","currency":"USD"},{"exOrEffDate":"05/26/2011","type":"CASH","amount":"$0.095","declarationDate":"02/21/2011","recordDate":"05/31/2011","paymentDate":"06/07/2011","currency":"USD"},{"exOrEffDate":"04/27/2011","type":"CASH","amount":"$0.095","declarationDate":"02/21/2011","recordDate":"04/29/2011","paymentDate":"05/06/2011","currency":"USD"},{"exOrEffDate":"03/29/2011","type":"CASH","amount":"$0.095","declarationDate":"02/21/2011","recordDate":"03/31/2011","paymentDate":"04/07/2011","currency":"USD"},{"exOrEffDate":"02/25/2011","type":"CASH","amount":"$0.095","declarationDate":"12/23/2010","recordDate":"03/01/2011","paymentDate":"03/08/2011","currency":"USD"},{"exOrEffDate":"01/28/2011","type":"CASH","amount":"$0.095","declarationDate":"12/23/2010","recordDate":"02/01/2011","paymentDate":"02/08/2011","currency":"USD"},{"exOrEffDate":"12/30/2010","type":"CASH","amount":"$0.095","declarationDate":"12/23/2010","recordDate":"01/03/2011","paymentDate":"01/10/2011","currency":"USD"},{"exOrEffDate":"11/29/2010","type":"CASH","amount":"$0.095","declarationDate":"09/21/2010","recordDate":"12/01/2010","paymentDate":"12/08/2010","currency":"USD"},{"exOrEffDate":"10/28/2010","type":"CASH","amount":"$0.095","declarationDate":"09/21/2010","recordDate":"11/01/2010","paymentDate":"11/08/2010","currency":"USD"},{"exOrEffDate":"09/29/2010","type":"CASH","amount":"$0.095","declarationDate":"09/21/2010","recordDate":"10/01/2010","paymentDate":"10/07/2010","currency":"USD"},{"exOrEffDate":"08/31/2010","type":"CASH","amount":"$0.096","declarationDate":"07/02/2010","recordDate":"09/02/2010","paymentDate":"09/07/2010","currency":"USD"},{"exOrEffDate":"08/31/2010","type":"CASH","amount":"$0.096","declarationDate":"07/02/2010","recordDate":"09/02/2010","paymentDate":"09/07/2010","currency":"USD"}]}},"message":null,"status":{"rCode":200,"bCodeMessage":null,"developerMessage":null}}