{"data":{"symbol":"MGIC","companyName":"Magic Software Enterprises Ltd. Ordinary Shares","stockType":"Ordinary Shares","exchange":"NASDAQ-GS","isNasdaqListed":true,"isNasdaq100":false,"isHeld":false,"primaryData":{"lastSalePrice":"$16.53","netChange":"-0.27","percentageChange":"-1.61%","deltaIndicator":"down","lastTradeTimestamp":"Feb 10, 2023","isRealTime":false,"bidPrice":"N/A","askPrice":"N/A","volume":"7,386"},"secondaryData":null,"marketStatus":"Closed","assetClass":"STOCKS","keyStats":null,"notifications":[]},"message":null,"status":{"rCode":200,"bCodeMessage":null,"developerMessage":null}}