{"data":{"symbol":"SWSS","companyName":"Springwater Special Situations Corp. Common stock","stockType":"Common stock","exchange":"NASDAQ-CM","isNasdaqListed":true,"isNasdaq100":false,"isHeld":false,"primaryData":{"lastSalePrice":"$10.2199","netChange":"+0.0099","percentageChange":"+0.1%","deltaIndicator":"up","lastTradeTimestamp":"Feb 10, 2023","isRealTime":false,"bidPrice":"N/A","askPrice":"N/A","volume":"196"},"secondaryData":null,"marketStatus":"Closed","assetClass":"STOCKS","keyStats":null,"notifications":[]},"message":null,"status":{"rCode":200,"bCodeMessage":null,"developerMessage":null}}