{"data":{"symbol":"GEGGL","companyName":"Great Elm Group, Inc.  7.25% Notes due 2027","stockType":"7.25% Notes due 2027 Exchange Traded Debt (Baby Bond)","exchange":"NASDAQ-GM","isNasdaqListed":true,"isNasdaq100":false,"isHeld":false,"primaryData":{"lastSalePrice":"$20.1476","netChange":"+0.1476","percentageChange":"+0.74%","deltaIndicator":"up","lastTradeTimestamp":"Feb 10, 2023","isRealTime":false,"bidPrice":"N/A","askPrice":"N/A","volume":"2,729"},"secondaryData":null,"marketStatus":"Closed","assetClass":"STOCKS","keyStats":null,"notifications":[]},"message":null,"status":{"rCode":200,"bCodeMessage":null,"developerMessage":null}}