{"data":{"dividendHeaderValues":[{"label":"EX-DIVIDEND DATE","value":"12/14/2022"},{"label":"DIVIDEND YIELD","value":"3.41%"},{"label":"ANNUAL DIVIDEND","value":"$2.92"},{"label":"P/E RATIO","value":"23.75"}],"exDividendDate":"12/14/2022","dividendPaymentDate":"12/29/2022","yield":"3.41%","annualizedDividend":"2.92","payoutRatio":"23.75","dividends":{"headers":{"exOrEffDate":"Ex/EFF DATE","type":"TYPE","amount":"CASH AMOUNT","declarationDate":"DECLARATION DATE","recordDate":"RECORD DATE","paymentDate":"PAYMENT DATE"},"rows":[{"exOrEffDate":"03/14/2023","type":"CASH","amount":"$0.75","declarationDate":"01/25/2023","recordDate":"03/15/2023","paymentDate":"03/30/2023","currency":"USD"},{"exOrEffDate":"12/14/2022","type":"CASH","amount":"$0.73","declarationDate":"10/25/2022","recordDate":"12/15/2022","paymentDate":"12/29/2022","currency":"USD"},{"exOrEffDate":"09/14/2022","type":"CASH","amount":"$0.73","declarationDate":"07/25/2022","recordDate":"09/15/2022","paymentDate":"09/29/2022","currency":"USD"},{"exOrEffDate":"06/14/2022","type":"CASH","amount":"$0.73","declarationDate":"04/27/2022","recordDate":"06/15/2022","paymentDate":"06/29/2022","currency":"USD"},{"exOrEffDate":"03/14/2022","type":"CASH","amount":"$0.73","declarationDate":"01/28/2022","recordDate":"03/15/2022","paymentDate":"03/30/2022","currency":"USD"},{"exOrEffDate":"12/14/2021","type":"CASH","amount":"$0.71","declarationDate":"10/26/2021","recordDate":"12/15/2021","paymentDate":"12/30/2021","currency":"USD"},{"exOrEffDate":"09/14/2021","type":"CASH","amount":"$0.71","declarationDate":"07/26/2021","recordDate":"09/15/2021","paymentDate":"09/29/2021","currency":"USD"},{"exOrEffDate":"06/14/2021","type":"CASH","amount":"$0.71","declarationDate":"04/27/2021","recordDate":"06/15/2021","paymentDate":"06/29/2021","currency":"USD"},{"exOrEffDate":"03/12/2021","type":"CASH","amount":"$0.71","declarationDate":"02/02/2021","recordDate":"03/15/2021","paymentDate":"03/30/2021","currency":"USD"},{"exOrEffDate":"12/14/2020","type":"CASH","amount":"$0.68","declarationDate":"10/26/2020","recordDate":"12/15/2020","paymentDate":"12/30/2020","currency":"USD"},{"exOrEffDate":"09/14/2020","type":"CASH","amount":"$0.68","declarationDate":"07/29/2020","recordDate":"09/15/2020","paymentDate":"09/29/2020","currency":"USD"},{"exOrEffDate":"06/11/2020","type":"CASH","amount":"$0.68","declarationDate":"04/29/2020","recordDate":"06/12/2020","paymentDate":"06/29/2020","currency":"USD"},{"exOrEffDate":"03/12/2020","type":"CASH","amount":"$0.68","declarationDate":"02/03/2020","recordDate":"03/13/2020","paymentDate":"03/30/2020","currency":"USD"},{"exOrEffDate":"12/12/2019","type":"CASH","amount":"$0.63","declarationDate":"10/23/2019","recordDate":"12/13/2019","paymentDate":"12/30/2019","currency":"USD"},{"exOrEffDate":"09/12/2019","type":"CASH","amount":"$0.63","declarationDate":"07/29/2019","recordDate":"09/13/2019","paymentDate":"09/27/2019","currency":"USD"},{"exOrEffDate":"06/13/2019","type":"CASH","amount":"$0.63","declarationDate":"05/01/2019","recordDate":"06/14/2019","paymentDate":"06/27/2019","currency":"USD"},{"exOrEffDate":"03/14/2019","type":"CASH","amount":"$0.63","declarationDate":"02/01/2019","recordDate":"03/15/2019","paymentDate":"03/28/2019","currency":"USD"},{"exOrEffDate":"12/13/2018","type":"CASH","amount":"$0.57","declarationDate":"10/24/2018","recordDate":"12/14/2018","paymentDate":"12/28/2018","currency":"USD"},{"exOrEffDate":"09/13/2018","type":"CASH","amount":"$0.57","declarationDate":"07/24/2018","recordDate":"09/14/2018","paymentDate":"09/27/2018","currency":"USD"},{"exOrEffDate":"06/14/2018","type":"CASH","amount":"$0.57","declarationDate":"04/30/2018","recordDate":"06/15/2018","paymentDate":"06/28/2018","currency":"USD"},{"exOrEffDate":"03/15/2018","type":"CASH","amount":"$0.57","declarationDate":"02/05/2018","recordDate":"03/16/2018","paymentDate":"03/29/2018","currency":"USD"},{"exOrEffDate":"12/14/2017","type":"CASH","amount":"$0.52","declarationDate":"10/25/2017","recordDate":"12/15/2017","paymentDate":"12/28/2017","currency":"USD"},{"exOrEffDate":"09/14/2017","type":"CASH","amount":"$0.52","declarationDate":"07/25/2017","recordDate":"09/15/2017","paymentDate":"09/28/2017","currency":"USD"},{"exOrEffDate":"06/14/2017","type":"CASH","amount":"$0.52","declarationDate":"05/01/2017","recordDate":"06/16/2017","paymentDate":"06/29/2017","currency":"USD"},{"exOrEffDate":"03/14/2017","type":"CASH","amount":"$0.52","declarationDate":"02/06/2017","recordDate":"03/16/2017","paymentDate":"03/30/2017","currency":"USD"},{"exOrEffDate":"12/13/2016","type":"CASH","amount":"$0.47","declarationDate":"10/31/2016","recordDate":"12/15/2016","paymentDate":"12/29/2016","currency":"USD"},{"exOrEffDate":"09/14/2016","type":"CASH","amount":"$0.47","declarationDate":"07/22/2016","recordDate":"09/16/2016","paymentDate":"09/29/2016","currency":"USD"},{"exOrEffDate":"06/14/2016","type":"CASH","amount":"$0.47","declarationDate":"04/27/2016","recordDate":"06/16/2016","paymentDate":"06/29/2016","currency":"USD"},{"exOrEffDate":"03/14/2016","type":"CASH","amount":"$0.43","declarationDate":"02/02/2016","recordDate":"03/16/2016","paymentDate":"03/30/2016","currency":"USD"},{"exOrEffDate":"12/14/2015","type":"CASH","amount":"$0.43","declarationDate":"10/26/2015","recordDate":"12/16/2015","paymentDate":"12/30/2015","currency":"USD"},{"exOrEffDate":"09/14/2015","type":"CASH","amount":"$0.43","declarationDate":"07/23/2015","recordDate":"09/16/2015","paymentDate":"09/29/2015","currency":"USD"},{"exOrEffDate":"06/12/2015","type":"CASH","amount":"$0.43","declarationDate":"04/24/2015","recordDate":"06/16/2015","paymentDate":"06/29/2015","currency":"USD"}]}},"message":null,"status":{"rCode":200,"bCodeMessage":null,"developerMessage":null}}