{"data":{"symbol":"AAN","companyName":"Aarons Holdings Company, Inc. Common Stock ","stockType":"Common Stock","exchange":"NYSE","isNasdaqListed":false,"isNasdaq100":false,"isHeld":false,"primaryData":{"lastSalePrice":"$14.64","netChange":"-0.24","percentageChange":"-1.61%","deltaIndicator":"down","lastTradeTimestamp":"Feb 10, 2023","isRealTime":false,"bidPrice":"N/A","askPrice":"N/A","volume":"152,869"},"secondaryData":null,"marketStatus":"Closed","assetClass":"STOCKS","keyStats":null,"notifications":[]},"message":null,"status":{"rCode":200,"bCodeMessage":null,"developerMessage":null}}