{"data":{"dividendHeaderValues":[{"label":"EX-DIVIDEND DATE","value":"03/12/2020"},{"label":"DIVIDEND YIELD","value":"N/A"},{"label":"ANNUAL DIVIDEND","value":"$0.08"},{"label":"P/E RATIO","value":"0"}],"exDividendDate":"03/12/2020","dividendPaymentDate":"03/27/2020","yield":"N/A","annualizedDividend":"0.08","payoutRatio":"N/A","dividends":{"headers":{"exOrEffDate":"Ex/EFF DATE","type":"TYPE","amount":"CASH AMOUNT","declarationDate":"DECLARATION DATE","recordDate":"RECORD DATE","paymentDate":"PAYMENT DATE"},"rows":[{"exOrEffDate":"03/12/2020","type":"CASH","amount":"$0.02","declarationDate":"03/03/2020","recordDate":"03/13/2020","paymentDate":"03/27/2020","currency":"USD"},{"exOrEffDate":"11/27/2019","type":"CASH","amount":"$0.02","declarationDate":"11/16/2019","recordDate":"11/29/2019","paymentDate":"12/16/2019","currency":"USD"},{"exOrEffDate":"08/28/2019","type":"CASH","amount":"$0.02","declarationDate":"08/10/2019","recordDate":"08/29/2019","paymentDate":"09/13/2019","currency":"USD"},{"exOrEffDate":"06/14/2019","type":"CASH","amount":"$0.09","declarationDate":"06/04/2019","recordDate":"06/17/2019","paymentDate":"06/28/2019","currency":"USD"},{"exOrEffDate":"03/13/2019","type":"CASH","amount":"$0.09","declarationDate":"02/27/2019","recordDate":"03/14/2019","paymentDate":"03/28/2019","currency":"USD"},{"exOrEffDate":"11/26/2018","type":"CASH","amount":"$0.09","declarationDate":"11/13/2018","recordDate":"11/27/2018","paymentDate":"12/14/2018","currency":"USD"},{"exOrEffDate":"08/23/2018","type":"CASH","amount":"$0.09","declarationDate":"08/09/2018","recordDate":"08/24/2018","paymentDate":"09/14/2018","currency":"USD"},{"exOrEffDate":"06/12/2018","type":"CASH","amount":"$0.09","declarationDate":"05/21/2018","recordDate":"06/13/2018","paymentDate":"06/28/2018","currency":"USD"},{"exOrEffDate":"03/13/2018","type":"CASH","amount":"$0.09","declarationDate":"03/08/2018","recordDate":"03/14/2018","paymentDate":"03/28/2018","currency":"USD"},{"exOrEffDate":"11/27/2017","type":"CASH","amount":"$0.09","declarationDate":"11/02/2017","recordDate":"11/28/2017","paymentDate":"12/15/2017","currency":"USD"},{"exOrEffDate":"08/11/2017","type":"CASH","amount":"$0.20","declarationDate":"07/28/2017","recordDate":"08/15/2017","paymentDate":"08/30/2017","currency":"USD"},{"exOrEffDate":"08/11/2017","type":"CASH","amount":"$0.075","declarationDate":"07/28/2017","recordDate":"08/15/2017","paymentDate":"09/15/2017","currency":"USD"},{"exOrEffDate":"05/24/2017","type":"CASH","amount":"$0.075","declarationDate":"05/12/2017","recordDate":"05/26/2017","paymentDate":"06/15/2017","currency":"USD"},{"exOrEffDate":"02/24/2017","type":"CASH","amount":"$0.075","declarationDate":"02/09/2017","recordDate":"02/28/2017","paymentDate":"03/15/2017","currency":"USD"},{"exOrEffDate":"11/23/2016","type":"CASH","amount":"$0.075","declarationDate":"11/07/2016","recordDate":"11/28/2016","paymentDate":"12/15/2016","currency":"USD"},{"exOrEffDate":"08/11/2016","type":"CASH","amount":"$0.075","declarationDate":"07/20/2016","recordDate":"08/15/2016","paymentDate":"09/15/2016","currency":"USD"},{"exOrEffDate":"05/23/2016","type":"CASH","amount":"$0.075","declarationDate":"05/02/2016","recordDate":"05/25/2016","paymentDate":"06/15/2016","currency":"USD"},{"exOrEffDate":"09/10/2008","type":"CASH","amount":"$0.10","declarationDate":"08/04/2008","recordDate":"09/12/2008","paymentDate":"09/26/2008","currency":"USD"},{"exOrEffDate":"06/11/2008","type":"CASH","amount":"$0.10","declarationDate":"04/24/2008","recordDate":"06/13/2008","paymentDate":"06/27/2008","currency":"USD"},{"exOrEffDate":"03/12/2008","type":"CASH","amount":"$0.38","declarationDate":"02/12/2008","recordDate":"03/14/2008","paymentDate":"03/28/2008","currency":"USD"},{"exOrEffDate":"11/29/2007","type":"CASH","amount":"$0.38","declarationDate":"11/08/2007","recordDate":"12/03/2007","paymentDate":"12/17/2007","currency":"USD"},{"exOrEffDate":"09/12/2007","type":"CASH","amount":"$0.38","declarationDate":"08/01/2007","recordDate":"09/14/2007","paymentDate":"09/28/2007","currency":"USD"},{"exOrEffDate":"06/13/2007","type":"CASH","amount":"$0.38","declarationDate":"05/07/2007","recordDate":"06/15/2007","paymentDate":"06/28/2007","currency":"USD"},{"exOrEffDate":"03/12/2007","type":"CASH","amount":"$0.38","declarationDate":"02/13/2007","recordDate":"03/14/2007","paymentDate":"03/28/2007","currency":"USD"},{"exOrEffDate":"11/29/2006","type":"CASH","amount":"$0.38","declarationDate":"11/16/2006","recordDate":"12/01/2006","paymentDate":"12/15/2006","currency":"USD"},{"exOrEffDate":"09/13/2006","type":"CASH","amount":"$0.38","declarationDate":"09/06/2006","recordDate":"09/15/2006","paymentDate":"09/29/2006","currency":"USD"},{"exOrEffDate":"06/13/2006","type":"CASH","amount":"$0.38","declarationDate":"05/16/2006","recordDate":"06/15/2006","paymentDate":"06/29/2006","currency":"USD"}]}},"message":null,"status":{"rCode":200,"bCodeMessage":null,"developerMessage":null}}