{"data":{"dividendHeaderValues":[{"label":"EX-DIVIDEND DATE","value":"10/07/2022"},{"label":"DIVIDEND YIELD","value":"2.09%"},{"label":"ANNUAL DIVIDEND","value":"$1.04"},{"label":"P/E RATIO","value":"21.34"}],"exDividendDate":"10/07/2022","dividendPaymentDate":"10/26/2022","yield":"2.09%","annualizedDividend":"1.04","payoutRatio":"21.34","dividends":{"headers":{"exOrEffDate":"Ex/EFF DATE","type":"TYPE","amount":"CASH AMOUNT","declarationDate":"DECLARATION DATE","recordDate":"RECORD DATE","paymentDate":"PAYMENT DATE"},"rows":[{"exOrEffDate":"10/07/2022","type":"CASH","amount":"$0.52","declarationDate":"09/26/2022","recordDate":"10/11/2022","paymentDate":"10/26/2022","currency":"USD"},{"exOrEffDate":"03/30/2022","type":"CASH","amount":"$0.50","declarationDate":"02/24/2022","recordDate":"03/31/2022","paymentDate":"04/20/2022","currency":"USD"},{"exOrEffDate":"10/07/2021","type":"CASH","amount":"$0.47","declarationDate":"09/22/2021","recordDate":"10/08/2021","paymentDate":"10/22/2021","currency":"USD"},{"exOrEffDate":"04/01/2021","type":"CASH","amount":"$0.43","declarationDate":"02/25/2021","recordDate":"04/05/2021","paymentDate":"04/21/2021","currency":"USD"},{"exOrEffDate":"12/17/2020","type":"CASH","amount":"$2.14","declarationDate":"12/03/2020","recordDate":"12/18/2020","paymentDate":"12/30/2020","currency":"USD"},{"exOrEffDate":"10/13/2020","type":"CASH","amount":"$0.40","declarationDate":"09/25/2020","recordDate":"10/14/2020","paymentDate":"10/29/2020","currency":"USD"},{"exOrEffDate":"03/31/2020","type":"CASH","amount":"$0.34","declarationDate":"02/27/2020","recordDate":"04/01/2020","paymentDate":"04/16/2020","currency":"USD"},{"exOrEffDate":"09/27/2019","type":"CASH","amount":"$0.32","declarationDate":"09/16/2019","recordDate":"09/30/2019","paymentDate":"10/17/2019","currency":"USD"},{"exOrEffDate":"03/27/2019","type":"CASH","amount":"$0.30","declarationDate":"02/21/2019","recordDate":"03/28/2019","paymentDate":"04/18/2019","currency":"USD"},{"exOrEffDate":"10/05/2018","type":"CASH","amount":"$0.28","declarationDate":"09/27/2018","recordDate":"10/09/2018","paymentDate":"10/19/2018","currency":"USD"},{"exOrEffDate":"03/28/2018","type":"CASH","amount":"$0.27","declarationDate":"02/28/2018","recordDate":"03/30/2018","paymentDate":"04/12/2018","currency":"USD"},{"exOrEffDate":"10/04/2017","type":"CASH","amount":"$0.25","declarationDate":"09/21/2017","recordDate":"10/05/2017","paymentDate":"10/17/2017","currency":"USD"},{"exOrEffDate":"03/29/2017","type":"CASH","amount":"$0.22","declarationDate":"02/23/2017","recordDate":"03/31/2017","paymentDate":"04/14/2017","currency":"USD"},{"exOrEffDate":"09/29/2016","type":"CASH","amount":"$0.20","declarationDate":"09/22/2016","recordDate":"10/03/2016","paymentDate":"10/14/2016","currency":"USD"},{"exOrEffDate":"03/29/2016","type":"CASH","amount":"$0.185","declarationDate":"02/18/2016","recordDate":"03/31/2016","paymentDate":"04/15/2016","currency":"USD"},{"exOrEffDate":"09/28/2015","type":"CASH","amount":"$0.18","declarationDate":"09/16/2015","recordDate":"09/30/2015","paymentDate":"10/14/2015","currency":"USD"},{"exOrEffDate":"03/04/2015","type":"CASH","amount":"$0.18","declarationDate":"02/24/2015","recordDate":"03/06/2015","paymentDate":"03/16/2015","currency":"USD"}]}},"message":null,"status":{"rCode":200,"bCodeMessage":null,"developerMessage":null}}