{"data":{"symbol":"LESL","companyName":"Leslie's, Inc. Common Stock","stockType":"Common Stock","exchange":"NASDAQ-GS","isNasdaqListed":true,"isNasdaq100":false,"isHeld":false,"primaryData":{"lastSalePrice":"$13.38","netChange":"-0.04","percentageChange":"-0.3%","deltaIndicator":"down","lastTradeTimestamp":"Feb 10, 2023","isRealTime":false,"bidPrice":"N/A","askPrice":"N/A","volume":"4,294,531"},"secondaryData":null,"marketStatus":"Closed","assetClass":"STOCKS","keyStats":null,"notifications":[]},"message":null,"status":{"rCode":200,"bCodeMessage":null,"developerMessage":null}}