{"data":{"dividendHeaderValues":[{"label":"EX-DIVIDEND DATE","value":"11/11/2022"},{"label":"DIVIDEND YIELD","value":"4.42%"},{"label":"ANNUAL DIVIDEND","value":"$1.12"},{"label":"P/E RATIO","value":"7.33"}],"exDividendDate":"11/11/2022","dividendPaymentDate":"12/15/2022","yield":"4.42%","annualizedDividend":"1.12","payoutRatio":"7.33","dividends":{"headers":{"exOrEffDate":"Ex/EFF DATE","type":"TYPE","amount":"CASH AMOUNT","declarationDate":"DECLARATION DATE","recordDate":"RECORD DATE","paymentDate":"PAYMENT DATE"},"rows":[{"exOrEffDate":"11/11/2022","type":"CASH","amount":"$0.28","declarationDate":"11/03/2022","recordDate":"11/14/2022","paymentDate":"12/15/2022","currency":"USD"},{"exOrEffDate":"11/10/2022","type":"CASH","amount":"$0.28","declarationDate":"11/03/2022","recordDate":"11/14/2022","paymentDate":"12/15/2022","currency":"USD"},{"exOrEffDate":"08/12/2022","type":"CASH","amount":"$0.28","declarationDate":"08/04/2022","recordDate":"08/15/2022","paymentDate":"09/15/2022","currency":"USD"},{"exOrEffDate":"05/13/2022","type":"CASH","amount":"$0.28","declarationDate":"05/05/2022","recordDate":"05/16/2022","paymentDate":"06/16/2022","currency":"USD"},{"exOrEffDate":"02/25/2022","type":"CASH","amount":"$0.28","declarationDate":"02/17/2022","recordDate":"02/28/2022","paymentDate":"03/17/2022","currency":"USD"},{"exOrEffDate":"11/19/2021","type":"CASH","amount":"$0.28","declarationDate":"11/11/2021","recordDate":"11/22/2021","paymentDate":"12/16/2021","currency":"USD"},{"exOrEffDate":"08/20/2021","type":"CASH","amount":"$0.28","declarationDate":"08/12/2021","recordDate":"08/23/2021","paymentDate":"09/13/2021","currency":"USD"}]}},"message":null,"status":{"rCode":200,"bCodeMessage":null,"developerMessage":null}}