{"data":{"symbol":"GPN","companyName":"Global Payments Inc. Common Stock","stockType":"Common Stock","exchange":"NYSE","isNasdaqListed":false,"isNasdaq100":false,"isHeld":false,"primaryData":{"lastSalePrice":"$117.88","netChange":"+6.24","percentageChange":"+5.59%","deltaIndicator":"up","lastTradeTimestamp":"Feb 10, 2023","isRealTime":false,"bidPrice":"N/A","askPrice":"N/A","volume":"3,204,300"},"secondaryData":null,"marketStatus":"Closed","assetClass":"STOCKS","keyStats":null,"notifications":[]},"message":null,"status":{"rCode":200,"bCodeMessage":null,"developerMessage":null}}