{"data":{"dividendHeaderValues":[{"label":"EX-DIVIDEND DATE","value":"N/A"},{"label":"DIVIDEND YIELD","value":"N/A"},{"label":"ANNUAL DIVIDEND","value":"N/A"},{"label":"P/E RATIO","value":"6.61"}],"exDividendDate":"N/A","dividendPaymentDate":"N/A","yield":"N/A","annualizedDividend":"N/A","payoutRatio":"6.61","dividends":{"headers":{"exOrEffDate":"Ex/EFF DATE","type":"TYPE","amount":"CASH AMOUNT","declarationDate":"DECLARATION DATE","recordDate":"RECORD DATE","paymentDate":"PAYMENT DATE"},"rows":[{"exOrEffDate":"12/21/2017","type":"CASH","amount":"$1.00","declarationDate":"12/08/2017","recordDate":"12/22/2017","paymentDate":"12/28/2017","currency":"USD"},{"exOrEffDate":"12/18/2015","type":"CASH","amount":"$1.00","declarationDate":"12/10/2015","recordDate":"12/22/2015","paymentDate":"12/30/2015","currency":"USD"},{"exOrEffDate":"12/31/2014","type":"CASH","amount":"$2.00","declarationDate":"12/15/2014","recordDate":"12/26/2014","paymentDate":"12/30/2014","currency":"USD"}]}},"message":null,"status":{"rCode":200,"bCodeMessage":null,"developerMessage":null}}