{"data":{"dividendHeaderValues":[{"label":"EX-DIVIDEND DATE","value":"12/29/2022"},{"label":"DIVIDEND YIELD","value":"1.12%"},{"label":"ANNUAL DIVIDEND","value":"N/A"},{"label":"P/E RATIO","value":"N/A"}],"exDividendDate":"12/29/2022","dividendPaymentDate":"01/09/2023","yield":"1.12%","annualizedDividend":"N/A","payoutRatio":"N/A","dividends":{"headers":{"exOrEffDate":"Ex/EFF DATE","type":"TYPE","amount":"CASH AMOUNT","declarationDate":"DECLARATION DATE","recordDate":"RECORD DATE","paymentDate":"PAYMENT DATE"},"rows":[{"exOrEffDate":"12/29/2022","type":"CASH","amount":"$0.245922","declarationDate":"12/28/2022","recordDate":"12/30/2022","paymentDate":"01/09/2023","currency":"USD"},{"exOrEffDate":"06/29/2022","type":"CASH","amount":"$0.019112","declarationDate":"06/28/2022","recordDate":"06/30/2022","paymentDate":"07/08/2022","currency":"USD"},{"exOrEffDate":"12/30/2021","type":"CASH","amount":"$0.001664","declarationDate":"12/29/2021","recordDate":"12/31/2021","paymentDate":"01/07/2022","currency":"USD"},{"exOrEffDate":"06/29/2021","type":"CASH","amount":"$0.010948","declarationDate":"06/28/2021","recordDate":"06/30/2021","paymentDate":"07/08/2021","currency":"USD"}]}},"message":null,"status":{"rCode":200,"bCodeMessage":null,"developerMessage":null}}