{"data":{"dividendHeaderValues":[{"label":"EX-DIVIDEND DATE","value":"02/02/2023"},{"label":"DIVIDEND YIELD","value":"3.9%"},{"label":"ANNUAL DIVIDEND","value":"$1.32"},{"label":"P/E RATIO","value":"11.24"}],"exDividendDate":"02/02/2023","dividendPaymentDate":"02/10/2023","yield":"3.9%","annualizedDividend":"1.32","payoutRatio":"11.24","dividends":{"headers":{"exOrEffDate":"Ex/EFF DATE","type":"TYPE","amount":"CASH AMOUNT","declarationDate":"DECLARATION DATE","recordDate":"RECORD DATE","paymentDate":"PAYMENT DATE"},"rows":[{"exOrEffDate":"02/02/2023","type":"CASH","amount":"$0.33","declarationDate":"01/24/2023","recordDate":"02/03/2023","paymentDate":"02/10/2023","currency":"USD"},{"exOrEffDate":"10/28/2022","type":"CASH","amount":"$0.33","declarationDate":"10/19/2022","recordDate":"10/31/2022","paymentDate":"11/10/2022","currency":"USD"},{"exOrEffDate":"07/29/2022","type":"CASH","amount":"$0.33","declarationDate":"07/19/2022","recordDate":"08/01/2022","paymentDate":"08/12/2022","currency":"USD"},{"exOrEffDate":"05/05/2022","type":"CASH","amount":"$0.33","declarationDate":"04/22/2022","recordDate":"05/06/2022","paymentDate":"05/13/2022","currency":"USD"},{"exOrEffDate":"02/03/2022","type":"CASH","amount":"$0.33","declarationDate":"01/18/2022","recordDate":"02/04/2022","paymentDate":"02/11/2022","currency":"USD"},{"exOrEffDate":"10/29/2021","type":"CASH","amount":"$0.33","declarationDate":"10/19/2021","recordDate":"11/01/2021","paymentDate":"11/12/2021","currency":"USD"},{"exOrEffDate":"08/05/2021","type":"CASH","amount":"$0.33","declarationDate":"07/23/2021","recordDate":"08/06/2021","paymentDate":"08/13/2021","currency":"USD"},{"exOrEffDate":"05/06/2021","type":"CASH","amount":"$0.33","declarationDate":"04/23/2021","recordDate":"05/07/2021","paymentDate":"05/14/2021","currency":"USD"},{"exOrEffDate":"02/04/2021","type":"CASH","amount":"$0.30","declarationDate":"01/21/2021","recordDate":"02/05/2021","paymentDate":"02/12/2021","currency":"USD"},{"exOrEffDate":"11/05/2020","type":"CASH","amount":"$0.28","declarationDate":"10/23/2020","recordDate":"11/06/2020","paymentDate":"11/13/2020","currency":"USD"},{"exOrEffDate":"08/06/2020","type":"CASH","amount":"$0.25","declarationDate":"07/24/2020","recordDate":"08/07/2020","paymentDate":"08/14/2020","currency":"USD"},{"exOrEffDate":"05/07/2020","type":"CASH","amount":"$0.25","declarationDate":"04/24/2020","recordDate":"05/08/2020","paymentDate":"05/15/2020","currency":"USD"},{"exOrEffDate":"01/31/2020","type":"CASH","amount":"$0.25","declarationDate":"01/21/2020","recordDate":"02/03/2020","paymentDate":"02/14/2020","currency":"USD"},{"exOrEffDate":"10/31/2019","type":"CASH","amount":"$0.22","declarationDate":"10/18/2019","recordDate":"11/01/2019","paymentDate":"11/15/2019","currency":"USD"},{"exOrEffDate":"08/01/2019","type":"CASH","amount":"$0.22","declarationDate":"07/19/2019","recordDate":"08/02/2019","paymentDate":"08/15/2019","currency":"USD"},{"exOrEffDate":"04/30/2019","type":"CASH","amount":"$0.22","declarationDate":"04/19/2019","recordDate":"05/01/2019","paymentDate":"05/15/2019","currency":"USD"},{"exOrEffDate":"02/14/2019","type":"CASH","amount":"$0.22","declarationDate":"01/28/2019","recordDate":"02/15/2019","paymentDate":"03/01/2019","currency":"USD"}]}},"message":null,"status":{"rCode":200,"bCodeMessage":null,"developerMessage":null}}