{"data":{"symbol":"CJJD","companyName":"China Jo-Jo Drugstores, Inc. (Cayman Islands) Ordinary Shares","stockType":"Ordinary Shares","exchange":"NASDAQ-CM","isNasdaqListed":true,"isNasdaq100":false,"isHeld":false,"primaryData":{"lastSalePrice":"$4.95","netChange":"+0.48","percentageChange":"+10.74%","deltaIndicator":"up","lastTradeTimestamp":"Feb 10, 2023","isRealTime":false,"bidPrice":"N/A","askPrice":"N/A","volume":"174,589"},"secondaryData":null,"marketStatus":"Closed","assetClass":"STOCKS","keyStats":null,"notifications":[]},"message":null,"status":{"rCode":200,"bCodeMessage":null,"developerMessage":null}}